namecheap/__init__.py
namecheap/client.py
namecheap/errors.py
namecheap/logging.py
namecheap/models.py
namecheap/_api/__init__.py
namecheap/_api/base.py
namecheap/_api/dns.py
namecheap/_api/domains.py
namecheap_cli/README.md
namecheap_cli/__init__.py
namecheap_cli/__main__.py
namecheap_cli/completion.py
namecheap_dns_tui/README.md
namecheap_dns_tui/__init__.py
namecheap_dns_tui/__main__.py
namecheap_dns_tui/assets/screenshot1.png
namecheap_dns_tui/assets/screenshot2.png
namecheap_dns_tui/assets/screenshot3.png
namecheap_dns_tui/assets/screenshot4.png
namecheap_python-1.0.6.dist-info/METADATA
namecheap_python-1.0.6.dist-info/WHEEL
namecheap_python-1.0.6.dist-info/entry_points.txt
namecheap_python-1.0.6.dist-info/licenses/LICENSE
namecheap_python-1.0.6.dist-info/RECORD
