Metadata-Version: 2.4
Name: namecheap-python
Version: 1.0.6
Summary: A friendly Python SDK for Namecheap API
Project-URL: Homepage, https://github.com/adriangalilea/namecheap-python
Project-URL: Repository, https://github.com/adriangalilea/namecheap-python
Project-URL: Issues, https://github.com/adriangalilea/namecheap-python/issues
Author-email: Adrian Galilea Delgado <adriangalilea@gmail.com>
License: MIT
License-File: LICENSE
Keywords: api,dns,domains,namecheap,sdk
Classifier: Development Status :: 4 - Beta
Classifier: Intended Audience :: Developers
Classifier: License :: OSI Approved :: MIT License
Classifier: Programming Language :: Python :: 3
Classifier: Programming Language :: Python :: 3.12
Classifier: Programming Language :: Python :: 3.13
Classifier: Topic :: Internet :: Name Service (DNS)
Classifier: Topic :: Software Development :: Libraries :: Python Modules
Classifier: Typing :: Typed
Requires-Python: >=3.12
Requires-Dist: httpx>=0.27.0
Requires-Dist: pydantic>=2.5.0
Requires-Dist: python-dotenv>=1.0.0
Requires-Dist: rich>=13.0.0
Requires-Dist: tldextract>=5.0.0
Requires-Dist: xmltodict>=0.13.0
Provides-Extra: all
Requires-Dist: click>=8.1.0; extra == 'all'
Requires-Dist: platformdirs>=4.0.0; extra == 'all'
Requires-Dist: pyyaml>=6.0.0; extra == 'all'
Requires-Dist: textual>=0.47.0; extra == 'all'
Provides-Extra: cli
Requires-Dist: click>=8.1.0; extra == 'cli'
Requires-Dist: platformdirs>=4.0.0; extra == 'cli'
Requires-Dist: pyyaml>=6.0.0; extra == 'cli'
Provides-Extra: dev
Requires-Dist: ruff>=0.7.0; extra == 'dev'
Provides-Extra: tui
Requires-Dist: textual>=0.47.0; extra == 'tui'
